frost/__init__.py
frost/client/__init__.py
frost/client/auth.py
frost/client/client.py
frost/client/headers.py
frost/client/objects.py
frost/client/events/__init__.py
frost/client/events/cogs.py
frost/client/events/events.py
frost/client/socketio/__init__.py
frost/client/socketio/base_client.py
frost/client/socketio/utils.py
frost/ext/__init__.py
frost/ext/cog.py
frost/ext/exceptions.py
frost/ext/handler.py
frost/server/__init__.py
frost/server/auth.py
frost/server/cogs.py
frost/server/headers.py
frost/server/logger.py
frost/server/objects.py
frost/server/server.py
frost/server/database/__init__.py
frost/server/database/db.py
frost/server/database/models.py
frost/server/socketio/__init__.py
frost/server/socketio/base_server.py
frost/server/socketio/utils.py
frost/server/storage/__init__.py
frost/server/storage/base.py
frost/server/storage/defaults.py
frost/server/storage/exceptions.py
frost/server/storage/models.py
tests/__init__.py
tests/__main__.py
tests/run_client.py
tests/run_server.py
pyfrost-0.2.1.dist-info/LICENSE
pyfrost-0.2.1.dist-info/METADATA
pyfrost-0.2.1.dist-info/WHEEL
pyfrost-0.2.1.dist-info/top_level.txt
pyfrost-0.2.1.dist-info/RECORD
